{
  "by_dimension": {
    "atomise": {
      "current_rows": 2,
      "open_accepted": 0
    },
    "consolidate": {
      "current_rows": 1,
      "open_accepted": 0
    },
    "design": {
      "current_rows": 176,
      "open_accepted": 14
    },
    "extract": {
      "current_rows": 1,
      "open_accepted": 0
    },
    "handoff": {
      "current_rows": 3,
      "open_accepted": 0
    },
    "merge": {
      "current_rows": 1,
      "open_accepted": 0
    },
    "model-fit": {
      "current_rows": 1,
      "open_accepted": 0
    },
    "naming": {
      "current_rows": 5,
      "open_accepted": 0
    },
    "plugin": {
      "current_rows": 27,
      "open_accepted": 0
    },
    "quality": {
      "current_rows": 963,
      "open_accepted": 57
    },
    "split": {
      "current_rows": 4,
      "open_accepted": 0
    },
    "tool-hygiene": {
      "current_rows": 1,
      "open_accepted": 0
    },
    "unknown": {
      "current_rows": 264,
      "open_accepted": 3
    }
  },
  "by_disposition": {
    "accepted": 74,
    "declined": 265,
    "fixed": 1038,
    "grandfathered": 72
  },
  "by_surface": {
    "design": {
      "current_rows": 14,
      "open_accepted": 0
    },
    "plugin": {
      "current_rows": 510,
      "open_accepted": 70
    },
    "query": {
      "current_rows": 27,
      "open_accepted": 0
    },
    "tooling": {
      "current_rows": 634,
      "open_accepted": 1
    },
    "unknown": {
      "current_rows": 264,
      "open_accepted": 3
    }
  },
  "current_rows": 1449,
  "generated_at": "2026-07-02T14:19:48.984491+00:00",
  "integrity_warnings": 0,
  "open_accepted": 74,
  "source_hash": "23a24498cd717cae0d92954b44e6e59f56f3f536751fcf39091208979424b02b",
  "total_events": 2585
}
