{
  "by_dimension": {
    "design": {
      "current_rows": 107,
      "open_accepted": 3
    },
    "naming": {
      "current_rows": 5,
      "open_accepted": 0
    },
    "quality": {
      "current_rows": 711,
      "open_accepted": 15
    },
    "unknown": {
      "current_rows": 258,
      "open_accepted": 0
    }
  },
  "by_disposition": {
    "accepted": 18,
    "declined": 161,
    "fixed": 831,
    "grandfathered": 71
  },
  "by_surface": {
    "plugin": {
      "current_rows": 325,
      "open_accepted": 0
    },
    "tooling": {
      "current_rows": 498,
      "open_accepted": 18
    },
    "unknown": {
      "current_rows": 258,
      "open_accepted": 0
    }
  },
  "current_rows": 1081,
  "generated_at": "2026-06-26T11:23:02.627178+00:00",
  "integrity_warnings": 0,
  "open_accepted": 18,
  "source_hash": "8b5e1b7ea7ad94661f4629e91d7f001ee93a900441f9cb88ed12576b9053eba0",
  "total_events": 1966
}
